MadMatrixLib/__init__.py
MadMatrixLib/mml.py
MadMatrixLib-0.1.dist-info/METADATA
MadMatrixLib-0.1.dist-info/WHEEL
MadMatrixLib-0.1.dist-info/top_level.txt
MadMatrixLib-0.1.dist-info/RECORD
