Metadata-Version: 2.1
Name: MadMatrixLib
Version: 0.1
Summary: Just a library '
Author: Gowtham
Classifier: Programming Language :: Python :: 3
Classifier: License :: OSI Approved :: MIT License
Classifier: Operating System :: OS Independent
